MANIFEST.in
README.rst
setup.cfg
setup.py
docs/CHANGES.txt
docs/CONTRIBUTORS.txt
docs/LICENSE.GPL
docs/LICENSE.txt
src/plomino/__init__.py
src/plomino.patternslib.egg-info/PKG-INFO
src/plomino.patternslib.egg-info/SOURCES.txt
src/plomino.patternslib.egg-info/dependency_links.txt
src/plomino.patternslib.egg-info/entry_points.txt
src/plomino.patternslib.egg-info/namespace_packages.txt
src/plomino.patternslib.egg-info/not-zip-safe
src/plomino.patternslib.egg-info/paster_plugins.txt
src/plomino.patternslib.egg-info/requires.txt
src/plomino.patternslib.egg-info/top_level.txt
src/plomino/patternslib/__init__.py
src/plomino/patternslib/configure.zcml
src/plomino/patternslib/testing.py
src/plomino/patternslib/testing.zcml
src/plomino/patternslib/browser/__init__.py
src/plomino/patternslib/browser/configure.zcml
src/plomino/patternslib/browser/css/__init__.py
src/plomino/patternslib/browser/css/chosen-sprite.png
src/plomino/patternslib/browser/css/chosen.css
src/plomino/patternslib/browser/javascript/__init__.py
src/plomino/patternslib/examples/github_issue_4/plomino_patternslib_issue_4.xml
src/plomino/patternslib/fields/__init__.py
src/plomino/patternslib/fields/chosen_edit.pt
src/plomino/patternslib/fields/chosen_read.pt
src/plomino/patternslib/fields/selection.py
src/plomino/patternslib/profiles/default/cssregistry.xml
src/plomino/patternslib/profiles/default/jsregistry.xml
src/plomino/patternslib/profiles/default/metadata.xml
src/plomino/patternslib/profiles/testing/metadata.xml
src/plomino/patternslib/tests/__init__.py
src/plomino/patternslib/tests/test_example.py