Metadata-Version: 1.0
Name: plomino.patternslib
Version: 0.5.8
Summary: A Plomino plugin that provides fields and other form elements built using the Patterns javascript library.
Home-page: https://github.com/plomino/plomino.patternslib
Author: Fulvio Casali
Author-email: fulviocasali@gmail.com
License: gpl
Keywords: Plomino,Patternslib,Patterns,Javascript,Fields
Platform: UNKNOWN
Classifier: Environment :: Web Environment
Classifier: Framework :: Plone
Classifier: Operating System :: OS Independent
Classifier: Programming Language :: Python
Classifier: Programming Language :: Python :: 2.6
Classifier: Topic :: Software Development :: Libraries :: Python Modules
